{
    "feat": "feature",
    "fix": "fix",
    "docs": "documentation",
    "test": "unittests",
    "ci": "CI/CD",
    "refactor": "refactor",
    "perf": "performance",
    "chore": "housekeeping",
    "revert": "revert",
    "wip": "WIP",
    "style": "codestyle",
    "config": "config",
    "parser": "parser",
    "tooling": "tooling",
    "cli": "cli",
    "gui": "gui",
    "core": "core",
    "audio": "audio",
    "tts": "tts",
    "sst": "sst",
    "nlp": "nlp",
    "plugins": "plugins",
    "localisation": "localisation",
    "resources": "resources",
    "release": "release",
    "breaking": "breaking change",
    "need_cc": "CC missing"
}